xhydro_lstm/__init__.py
xhydro_lstm/create_datasets.py
xhydro_lstm/lstm_controller.py
xhydro_lstm/lstm_functions.py
xhydro_lstm/lstm_static.py
xhydro_lstm-0.1.1.dist-info/LICENSE
xhydro_lstm-0.1.1.dist-info/WHEEL
xhydro_lstm-0.1.1.dist-info/METADATA
xhydro_lstm-0.1.1.dist-info/RECORD
