Metadata-Version: 2.3
Name: xhydro-lstm
Version: 0.1.1
Summary: Hydrological modelling using LSTMs.
Keywords: xhydro-lstm
Author-email: Richard Arsenault <Richard.Arsenault@etsmtl.ca>
Maintainer-email: Richard Arsenault <Richard.Arsenault@etsmtl.ca>, Trevor James Smith <smith.trevorj@ouranos.ca>, Gabriel Rondeau-Genesse <rondeau-genesse.gabriel@ouranos.ca>
Requires-Python: >=3.9.0
Classifier: Development Status :: 2 - Pre-Alpha
Classifier: Intended Audience :: Developers
Classifier: License :: OSI Approved :: Apache Software License
Classifier: Natural Language :: English
Classifier: Operating System :: OS Independent
Classifier: Programming Language :: Python :: 3
Classifier: Programming Language :: Python :: 3 :: Only
Classifier: Programming Language :: Python :: 3.9
Classifier: Programming Language :: Python :: 3.10
Classifier: Programming Language :: Python :: 3.11
Classifier: Programming Language :: Python :: 3.12
Classifier: Programming Language :: Python :: Implementation :: CPython
Requires-Dist: charset-normalizer >=3.1.0
Requires-Dist: netcdf4
Requires-Dist: numpy >=1.24.0
Requires-Dist: scikit-learn >=1.2.0
Requires-Dist: tensorflow >=2.10
Requires-Dist: xarray >=2023.11.0
Requires-Dist: xhydro
Requires-Dist: xhydro-lstm[dev] ; extra == "all"
Requires-Dist: xhydro-lstm[docs] ; extra == "all"
Requires-Dist: blackdoc ==0.3.9 ; extra == "dev"
Requires-Dist: bump-my-version >=0.30.1 ; extra == "dev"
Requires-Dist: coverage >=7.5.0 ; extra == "dev"
Requires-Dist: flake8 >=7.1.1 ; extra == "dev"
Requires-Dist: flake8-rst-docstrings >=0.3.0 ; extra == "dev"
Requires-Dist: flit >=3.10.1,<4.0 ; extra == "dev"
Requires-Dist: isort ==6.0.1 ; extra == "dev"
Requires-Dist: mypy >=1.14.1 ; extra == "dev"
Requires-Dist: numpydoc >=1.8.0 ; extra == "dev"
Requires-Dist: pip >=25.0 ; extra == "dev"
Requires-Dist: pooch >=1.8.0 ; extra == "dev"
Requires-Dist: pre-commit >=3.5.0 ; extra == "dev"
Requires-Dist: pytest >=8.3.2 ; extra == "dev"
Requires-Dist: pytest-cov >=5.0.0 ; extra == "dev"
Requires-Dist: ruff >=0.9.0 ; extra == "dev"
Requires-Dist: tox >=4.24.1 ; extra == "dev"
Requires-Dist: watchdog >=4.0.0 ; extra == "dev"
Requires-Dist: ipykernel ; extra == "docs"
Requires-Dist: ipython ; extra == "docs"
Requires-Dist: jupyter_client ; extra == "docs"
Requires-Dist: nbsphinx >=0.9.5 ; extra == "docs"
Requires-Dist: sphinx >=7.1.0,<8.2.0 ; extra == "docs"
Requires-Dist: sphinx-autodoc-typehints ; extra == "docs"
Requires-Dist: sphinx-codeautolink ; extra == "docs"
Requires-Dist: sphinx-copybutton ; extra == "docs"
Requires-Dist: sphinx-intl ; extra == "docs"
Requires-Dist: sphinx-rtd-theme >=1.0 ; extra == "docs"
Project-URL: Changelog, https://xhydro-lstm.readthedocs.io/en/stable/changelog.html
Project-URL: Homepage, https://xhydro_lstm.readthedocs.io/
Project-URL: Issue tracker, https://github.com/hydrologie/xhydro-lstm/issues
Project-URL: Source, https://github.com/hydrologie/xhydro-lstm
Provides-Extra: all
Provides-Extra: dev
Provides-Extra: docs
